[{"id":1618009820408,"pergunta":"Quanto é 3 + 3?","alunosPresentes":[{"id":1618009778443,"nome":"Aislan Almeida"}]},{"id":1618010801751,"pergunta":"Quanto é 4 + 4?","alunosPresentes":[{"id":1618009778443,"nome":"Aislan Almeida"},{"id":1618010688801,"nome":"José da Silva"}]},{"id":1618010858837,"pergunta":"Quanto é 45+ 45?","alunosPresentes":[{"id":1618009778443,"nome":"Aislan Almeida"},{"id":1618010688801,"nome":"José da Silva"}]},{"id":1618012006193,"pergunta":"Quanto é 7 + 7?","alunosPresentes":[{"id":1618009778443,"nome":"Aislan Almeida"},{"id":1618010688801,"nome":"José da Silva"},{"id":1618011942185,"nome":"Fernando Guimaraes"}]}]